tormysql/__init__.py
tormysql/client.py
tormysql/connections.py
tormysql/cursor.py
tormysql/helpers.py
tormysql/log.py
tormysql/pool.py
tormysql/util.py
tormysql/platform/__init__.py
tormysql/platform/asyncio.py
tormysql/platform/tornado.py
zoom_tormysql-0.4.2.dist-info/LICENSE
zoom_tormysql-0.4.2.dist-info/METADATA
zoom_tormysql-0.4.2.dist-info/WHEEL
zoom_tormysql-0.4.2.dist-info/top_level.txt
zoom_tormysql-0.4.2.dist-info/RECORD
