Metadata-Version: 2.1
Name: zoom-tormysql
Version: 0.4.2
Summary: Tornado asynchronous MySQL Driver
Home-page: https://github.com/snower/TorMySQL
Author: snower, mosquito
Author-email: sujian199@gmail.com, me@mosquito.su
License: MIT
Keywords: zoomcatalog
Platform: UNKNOWN
Requires-Dist: tornado (>=5)
Requires-Dist: PyMySQL (>=0.7.10)
Requires-Dist: greenlet (>=0.4.2)
